commitizen_wails/__init__.py
commitizen_wails/provider.py
commitizen_wails/types.py
commitizen_wails-0.2.2.dist-info/METADATA
commitizen_wails-0.2.2.dist-info/WHEEL
commitizen_wails-0.2.2.dist-info/entry_points.txt
commitizen_wails-0.2.2.dist-info/licenses/LICENSE
commitizen_wails-0.2.2.dist-info/RECORD
