Metadata-Version: 2.3
Name: commitizen-wails
Version: 0.2.2
Summary: A commitizen version provider for Wails.
Project-URL: Homepage, https://github.com/YogiLiu/commitizen-wails
Project-URL: Documentation, https://github.com/YogiLiu/commitizen-wails
Project-URL: Repository, https://github.com/YogiLiu/commitizen-wails
Project-URL: Issues, https://github.com/YogiLiu/commitizen-wails/issues
Project-URL: Changelog, https://github.com/YogiLiu/commitizen-wails/blob/main/CHANGELOG.md
Author-email: YogiLiu <YogiLiu@outlook.com>
License-File: LICENSE
Keywords: commitizen,wails
Classifier: Development Status :: 4 - Beta
Classifier: Intended Audience :: Developers
Classifier: License :: OSI Approved :: MIT License
Classifier: Programming Language :: Python :: 3.8
Classifier: Programming Language :: Python :: 3.9
Classifier: Programming Language :: Python :: 3.10
Classifier: Programming Language :: Python :: 3.11
Classifier: Programming Language :: Python :: 3.12
Requires-Python: >=3.8
Requires-Dist: commitizen>=3.29.0
